libsocket/__init__.py
libsocket/libsocket.py
libsocket/py.typed
libsocket-1.31.0.dist-info/LICENSE.md
libsocket-1.31.0.dist-info/METADATA
libsocket-1.31.0.dist-info/WHEEL
libsocket-1.31.0.dist-info/top_level.txt
libsocket-1.31.0.dist-info/RECORD
