Metadata-Version: 2.1
Name: libsocket
Version: 1.31.0
Summary: A socket library that facilitates communication between python client and server.
Home-page: https://github.com/Les-Venogeois/libsocket
Author: Chaxiraxi - nem013
Author-email: ChaxiraxiCH@protonmail.ch
License: UNKNOWN
Platform: UNKNOWN
Classifier: Programming Language :: Python :: 3
Classifier: License :: OSI Approved :: GNU General Public License v3 (GPLv3)
Classifier: Operating System :: OS Independent
Classifier: Intended Audience :: Developers
Requires-Dist: pycryptodome
